lastfm_backup.py
lastfm_backup-1.0.1.data/scripts/lastfm_backup.py
lastfm_backup-1.0.1.dist-info/LICENSE.txt
lastfm_backup-1.0.1.dist-info/METADATA
lastfm_backup-1.0.1.dist-info/WHEEL
lastfm_backup-1.0.1.dist-info/top_level.txt
lastfm_backup-1.0.1.dist-info/RECORD
