Metadata-Version: 2.1
Name: lastfm-backup
Version: 1.0.1
Summary: Last.fm scrobbles backup
Home-page: https://github.com/iiiypuk/lastfm-backup
Author: Alexander Popov
Author-email: iiiypuk@fastmail.fm
License: Unlicense
Keywords: last.fm,lastfm,backup
Platform: any
Classifier: License :: Public Domain
Classifier: Programming Language :: Python :: 3
Classifier: Operating System :: OS Independent
Requires-Python: >=3.0
